_distorm3.cp310-win_amd64.pyd
distorm3/__init__.py
distorm3/__main__.py
distorm3/_generated.py
distorm3/__pycache__/__init__.cpython-310.opt-1.pyc
distorm3/__pycache__/__main__.cpython-310.opt-1.pyc
distorm3/__pycache__/_generated.cpython-310.opt-1.pyc
distorm3s-3.5.4.dist-info/licenses/COPYING
distorm3s-3.5.4.dist-info/licenses/LICENSE
distorm3s-3.5.4.dist-info/METADATA
distorm3s-3.5.4.dist-info/WHEEL
distorm3s-3.5.4.dist-info/top_level.txt
distorm3s-3.5.4.dist-info/RECORD
