Metadata-Version: 2.4
Name: distorm3s
Version: 3.5.4
Summary: The goal of diStorm3 is to decode x86/AMD64 binary streams and return a structure that describes each instruction.
Home-page: https://github.com/gdabah/distorm/
Download-URL: https://github.com/gdabah/distorm/
Author: Gil Dabah
Author-email: distorm@gmail.com
Maintainer: Gil Dabah
Maintainer-email: distorm@gmail.com
Platform: cygwin
Platform: win
Platform: linux
Platform: macosx
Classifier: License :: OSI Approved :: BSD License
Classifier: Development Status :: 5 - Production/Stable
Classifier: Intended Audience :: Developers
Classifier: Natural Language :: English
Classifier: Operating System :: Microsoft :: Windows
Classifier: Operating System :: MacOS :: MacOS X
Classifier: Operating System :: POSIX :: Linux
Classifier: Programming Language :: Python :: 3.10
Classifier: Programming Language :: Python :: 3.11
Classifier: Programming Language :: Python :: 3.12
Classifier: Topic :: Software Development :: Disassemblers
Classifier: Topic :: Software Development :: Libraries :: Python Modules
Requires-Python: >=3.6
